{
  "completed": "2023-12-07T08:59:50.713894Z",
  "periodic": true,
  "started": "2023-12-07T08:59:24.481693Z",
  "versions": [
    {
      "filename": "setuptools-69.0.2-py3-none-any.whl",
      "found_date": "2023-12-07T08:59:26.533135Z",
      "release_date": "2023-11-21T19:00:58.000000Z",
      "source": "periodic"
    },
    {
      "filename": "setuptools-69.0.1-py3-none-any.whl",
      "found_date": "2023-12-07T08:59:33.911299Z",
      "release_date": "2023-11-21T10:57:28.000000Z",
      "source": "periodic"
    },
    {
      "filename": "setuptools-69.0.0-py3-none-any.whl",
      "found_date": "2023-12-07T08:59:40.269178Z",
      "release_date": "2023-11-20T17:49:20.000000Z",
      "source": "periodic"
    },
    {
      "filename": "setuptools-68.2.2-py3-none-any.whl",
      "found_date": "2023-12-07T08:59:45.415573Z",
      "release_date": "2023-09-12T17:22:04.000000Z",
      "source": "periodic"
    }
  ]
}